WebsocketServer/CLI.py
WebsocketServer/WebsocketServer.py
WebsocketServer/__init__.py
WebsocketServer/basic_types.py
websocketlib-0.2.5.dist-info/licenses/LICENSE
websocketlib-0.2.5.dist-info/METADATA
websocketlib-0.2.5.dist-info/WHEEL
websocketlib-0.2.5.dist-info/entry_points.txt
websocketlib-0.2.5.dist-info/top_level.txt
websocketlib-0.2.5.dist-info/RECORD
