Metadata-Version: 2.4
Name: WebsocketLib
Version: 0.2.5
Summary: A websocket server interface. Easy to use.
Author: Erri4
License: Copyright © Erri4, 2025
Project-URL: Homepage, https://github.com/erri4/WebsocketServer
Project-URL: Bug Tracker, https://github.com/erri4/WebsocketServer/issues
Classifier: License :: Other/Proprietary License
Requires-Python: >=3.8
License-File: LICENSE
Dynamic: license-file
